graphs_gmather2/__init__.py
graphs_gmather2/heapq.py
graphs_gmather2/sp.py
graphs_gmather2-0.0.1.dist-info/METADATA
graphs_gmather2-0.0.1.dist-info/WHEEL
graphs_gmather2-0.0.1.dist-info/RECORD
