Metadata-Version: 2.3
Name: graphs_gmather2
Version: 0.0.1
Summary: The primary purpose of this package is the implementation of Dijkstra's Shortest Path which is an algorithm that finds the shortest path between a source vertex and a target vertex in an undirected graph.
Project-URL: Homepage, https://github.com/Gage53211/Homework_4
Author: Gage Mather
Classifier: License :: OSI Approved :: MIT License
Classifier: Operating System :: OS Independent
Classifier: Programming Language :: Python :: 3
Requires-Python: >=3.7
